AugX/__init__.py
AugX/augment.py
augx-0.2.0.dist-info/licenses/LICENSE.txt
augx-0.2.0.dist-info/METADATA
augx-0.2.0.dist-info/WHEEL
augx-0.2.0.dist-info/top_level.txt
augx-0.2.0.dist-info/RECORD
