Metadata-Version: 2.4
Name: AugX
Version: 0.2.0
Summary: Simple image augmentation utility
Author-email: Xopse <shivangjain98@gmail.com>
Project-URL: Homepage, https://github.com/Xopse
Requires-Python: >=3.7
License-File: LICENSE.txt
Requires-Dist: opencv-python
Requires-Dist: numpy
Dynamic: license-file
